htmy-0.10.2.dist-info/METADATA
htmy-0.10.2.dist-info/WHEEL
htmy-0.10.2.dist-info/entry_points.txt
htmy-0.10.2.dist-info/licenses/LICENSE
htmy/__init__.py
htmy/core.py
htmy/error_boundary.py
htmy/etree.py
htmy/function_component.py
htmy/html.py
htmy/i18n.py
htmy/io.py
htmy/md/__init__.py
htmy/md/core.py
htmy/md/typing.py
htmy/py.typed
htmy/renderer/__init__.py
htmy/renderer/baseline.py
htmy/renderer/context.py
htmy/renderer/default.py
htmy/renderer/typing.py
htmy/snippet.py
htmy/tag.py
htmy/typing.py
htmy/utils.py
htmy-0.10.2.dist-info/RECORD
