Metadata-Version: 2.4
Name: htmy
Version: 0.10.2
Summary: Async, pure-Python server-side rendering engine.
Author-Email: Peter Volf <do.volfp@gmail.com>
License-Expression: MIT
Requires-Python: >=3.10
Requires-Dist: anyio<5,>=4.7.0
Requires-Dist: async-lru<3,>=2.0.5
Requires-Dist: markdown<4,>=3.8
Provides-Extra: lxml
Requires-Dist: lxml>=6.0.0; extra == "lxml"
